typed_dig/__init__.py
typed_dig/_dig.py
typed_dig-0.1.0.dist-info/LICENSE
typed_dig-0.1.0.dist-info/METADATA
typed_dig-0.1.0.dist-info/WHEEL
typed_dig-0.1.0.dist-info/RECORD
