Metadata-Version: 2.1
Name: typed-dig
Version: 0.1.0
Summary: A small Python library that provides a ruby-like dig function for accessing nested members of dictionaries (and "dict-like" structures, which support the __getitem__ method).
Home-page: https://github.com/demize/typed-dig
License: MIT
Author: demize
Author-email: demize@unstable.systems
Maintainer: demize
Maintainer-email: demize@unstable.systems
Requires-Python: >=3.10,<4.0
Classifier: License :: OSI Approved :: MIT License
Classifier: Programming Language :: Python :: 3
Classifier: Programming Language :: Python :: 3.10
Classifier: Programming Language :: Python :: 3.11
Classifier: Programming Language :: Python :: 3.12
Project-URL: Repository, https://github.com/demize/typed-dig
